askgpt/__init__.py
askgpt/api.py
askgpt/cli.py
askgpt/data/README.md
askgpt/data/__init__.py
askgpt/data/builtin_skills/__init__.py
askgpt/data/builtin_skills/auditing-security/SKILL.md
askgpt/data/builtin_skills/checking-code-formatting/SKILL.md
askgpt/data/builtin_skills/code-formatting-checker/SKILL.md
askgpt/data/builtin_skills/generating-readmes/SKILL.md
askgpt/data/builtin_skills/writing-release-notes/SKILL.md
askgpt/data/shortcuts.md
askgpt/data/tips.md
askgpt/data/welcome.md
askgpt/modules/agent_loader.py
askgpt/modules/cascade_command_loader.py
askgpt/modules/command_loader.py
askgpt/modules/config_integration.py
askgpt/modules/config_loader.py
askgpt/modules/config_manager.py
askgpt/modules/config_validation.py
askgpt/modules/constants.py
askgpt/modules/coordinator.py
askgpt/modules/data_types.py
askgpt/modules/files.py
askgpt/modules/hook_executor.py
askgpt/modules/hook_executor_v2.py
askgpt/modules/hook_manager.py
askgpt/modules/hook_manager_simplified.py
askgpt/modules/hook_types.py
askgpt/modules/interactive_mode.py
askgpt/modules/mcp_session_manager.py
askgpt/modules/model_provider_config.py
askgpt/modules/model_providers.py
askgpt/modules/nano_agent.py
askgpt/modules/nano_agent_runner.py
askgpt/modules/nano_agent_tools.py
askgpt/modules/ollama_wrapper.py
askgpt/modules/output_formats.py
askgpt/modules/provider_config.py
askgpt/modules/provider_config_updated.py
askgpt/modules/provider_implementations.py
askgpt/modules/session_manager.py
askgpt/modules/skill_loader.py
askgpt/modules/token_tracking.py
askgpt/modules/typing_fix.py
askgpt/modules/user_tools.py
askgpt/py.typed
askgpt/web_server.py
askgpt-2.0.0.dist-info/WHEEL
askgpt-2.0.0.dist-info/entry_points.txt
askgpt-2.0.0.dist-info/METADATA
askgpt-2.0.0.dist-info/RECORD
