Metadata-Version: 2.3
Name: askgpt
Version: 2.0.0
Summary: askGPT - Multi-provider AI agent CLI with offline-first support
Author: Meir Michanie
Author-email: Meir Michanie <meirm@riunx.com>
Requires-Dist: typer>=0.9.0
Requires-Dist: rich>=13.0.0
Requires-Dist: openai>=2.0.0
Requires-Dist: openai-agents>=0.6.0
Requires-Dist: requests>=2.28.0
Requires-Dist: prompt-toolkit>=3.0.0
Requires-Dist: pyyaml>=6.0.2
Requires-Dist: ollama>=0.1.0
Requires-Dist: aiohttp>=3.9.0
Requires-Dist: fastapi>=0.115.0
Requires-Dist: uvicorn[standard]>=0.30.0
Requires-Dist: websockets>=13.0
Requires-Dist: python-multipart>=0.0.9
Requires-Dist: pytest ; extra == 'test'
Requires-Dist: pytest-asyncio>=0.23.0 ; extra == 'test'
Requires-Dist: openai>=1.0.0 ; extra == 'test'
Requires-Dist: fastapi>=0.115.0 ; extra == 'web'
Requires-Dist: uvicorn[standard]>=0.30.0 ; extra == 'web'
Requires-Dist: websockets>=13.0 ; extra == 'web'
Requires-Dist: python-multipart>=0.0.9 ; extra == 'web'
Requires-Python: >=3.12
Provides-Extra: test
Provides-Extra: web
